odoo/addons/project_task_default_stage/README.rst
odoo/addons/project_task_default_stage/__init__.py
odoo/addons/project_task_default_stage/__manifest__.py
odoo/addons/project_task_default_stage/data/project_data.xml
odoo/addons/project_task_default_stage/i18n/bg.po
odoo/addons/project_task_default_stage/i18n/ca.po
odoo/addons/project_task_default_stage/i18n/cs_CZ.po
odoo/addons/project_task_default_stage/i18n/de.po
odoo/addons/project_task_default_stage/i18n/el_GR.po
odoo/addons/project_task_default_stage/i18n/en.po
odoo/addons/project_task_default_stage/i18n/es.po
odoo/addons/project_task_default_stage/i18n/es_AR.po
odoo/addons/project_task_default_stage/i18n/es_CO.po
odoo/addons/project_task_default_stage/i18n/es_MX.po
odoo/addons/project_task_default_stage/i18n/fi.po
odoo/addons/project_task_default_stage/i18n/fr.po
odoo/addons/project_task_default_stage/i18n/fr_FR.po
odoo/addons/project_task_default_stage/i18n/gl.po
odoo/addons/project_task_default_stage/i18n/hr.po
odoo/addons/project_task_default_stage/i18n/hu.po
odoo/addons/project_task_default_stage/i18n/it.po
odoo/addons/project_task_default_stage/i18n/nb.po
odoo/addons/project_task_default_stage/i18n/nb_NO.po
odoo/addons/project_task_default_stage/i18n/nl.po
odoo/addons/project_task_default_stage/i18n/nl_NL.po
odoo/addons/project_task_default_stage/i18n/pl.po
odoo/addons/project_task_default_stage/i18n/project_task_default_stage.pot
odoo/addons/project_task_default_stage/i18n/pt.po
odoo/addons/project_task_default_stage/i18n/pt_BR.po
odoo/addons/project_task_default_stage/i18n/pt_PT.po
odoo/addons/project_task_default_stage/i18n/ru.po
odoo/addons/project_task_default_stage/i18n/sk.po
odoo/addons/project_task_default_stage/i18n/sl.po
odoo/addons/project_task_default_stage/i18n/tr.po
odoo/addons/project_task_default_stage/i18n/zh_CN.po
odoo/addons/project_task_default_stage/models/__init__.py
odoo/addons/project_task_default_stage/models/project.py
odoo14_addon_project_task_default_stage-14.0.1.1.0.dist-info/METADATA
odoo14_addon_project_task_default_stage-14.0.1.1.0.dist-info/WHEEL
odoo14_addon_project_task_default_stage-14.0.1.1.0.dist-info/top_level.txt
odoo14_addon_project_task_default_stage-14.0.1.1.0.dist-info/RECORD
